consolex/__init__.py
consolex/consolex.py
consolex-2.0.dist-info/LICENSE
consolex-2.0.dist-info/METADATA
consolex-2.0.dist-info/WHEEL
consolex-2.0.dist-info/top_level.txt
consolex-2.0.dist-info/RECORD
