Metadata-Version: 2.1
Name: consolex
Version: 2.0
Summary: A modern console logging module for Python but similar to JavaScript
Home-page: https://github.com/shadowchaser/consolepy
Author: Əli Zülbalayev
Author-email: pulixbot@gmail.com
Classifier: Programming Language :: Python :: 3
Classifier: License :: OSI Approved :: MIT License
Classifier: Operating System :: OS Independent
Requires-Python: >=3.6
License-File: LICENSE
